tk_double_scale/__init__.py
tk_double_scale/double_scale.py
tk_double_scale-0.0.3.dist-info/METADATA
tk_double_scale-0.0.3.dist-info/WHEEL
tk_double_scale-0.0.3.dist-info/licenses/LICENSE
tk_double_scale-0.0.3.dist-info/RECORD
