Metadata-Version: 2.4
Name: tk_double_scale
Version: 0.0.3
Summary: A tkinter widget
Project-URL: Homepage, https://github.com/yannprada/tk_double_scale
Project-URL: Issues, https://github.com/yannprada/tk_double_scale/issues
Author-email: Yannick Pradayrol <pradayrol.yannick@gmail.com>
License-Expression: GPL-3.0-only
License-File: LICENSE
Classifier: Operating System :: OS Independent
Classifier: Programming Language :: Python :: 3
Requires-Python: >=3.13.3
Requires-Dist: pillow>=11.3.0
